delve/__init__.py
delve/client.py
delve/configuration.py
delve/console.py
delve/graph.py
delve/prompts.py
delve/py.typed
delve/result.py
delve/routing.py
delve/state.py
delve/utils.py
delve/adapters/__init__.py
delve/adapters/base.py
delve/adapters/csv_adapter.py
delve/adapters/dataframe_adapter.py
delve/adapters/json_adapter.py
delve/adapters/langsmith_adapter.py
delve/cli/__init__.py
delve/cli/main.py
delve/cli/utils.py
delve/core/__init__.py
delve/core/batch_generator.py
delve/core/classifier.py
delve/core/data_loader.py
delve/core/document_labeler.py
delve/core/results_saver.py
delve/core/summarizer.py
delve/core/taxonomy_generator.py
delve/core/taxonomy_reviewer.py
delve/core/taxonomy_updater.py
delve/exporters/__init__.py
delve/exporters/base.py
delve/exporters/csv_exporter.py
delve/exporters/json_exporter.py
delve/exporters/markdown_exporter.py
delve/exporters/metadata_exporter.py
delve_taxonomy-0.1.12.dist-info/licenses/LICENSE
delve_taxonomy-0.1.12.dist-info/METADATA
delve_taxonomy-0.1.12.dist-info/WHEEL
delve_taxonomy-0.1.12.dist-info/entry_points.txt
delve_taxonomy-0.1.12.dist-info/top_level.txt
delve_taxonomy-0.1.12.dist-info/RECORD
