Metadata-Version: 2.4
Name: delve-taxonomy
Version: 0.1.12
Summary: AI-powered taxonomy generation for your data
Author-email: Andres Torres <torres.andres87@gmail.com>
License: MIT
Keywords: taxonomy,classification,nlp,ai,langchain,langgraph
Classifier: Development Status :: 4 - Beta
Classifier: Intended Audience :: Developers
Classifier: Intended Audience :: Science/Research
Classifier: License :: OSI Approved :: MIT License
Classifier: Programming Language :: Python :: 3
Classifier: Programming Language :: Python :: 3.9
Classifier: Programming Language :: Python :: 3.10
Classifier: Programming Language :: Python :: 3.11
Classifier: Programming Language :: Python :: 3.12
Classifier: Topic :: Scientific/Engineering :: Artificial Intelligence
Classifier: Topic :: Text Processing :: Linguistic
Requires-Python: >=3.9
License-File: LICENSE
Requires-Dist: langgraph>=0.2.6
Requires-Dist: langchain>=0.2.14
Requires-Dist: langchain-anthropic>=0.1.23
Requires-Dist: langchain-openai>=0.1.22
Requires-Dist: langchain-fireworks>=0.1.7
Requires-Dist: langchain-community>=0.2.17
Requires-Dist: langsmith>=0.1.0
Requires-Dist: python-dotenv>=1.0.1
Requires-Dist: click>=8.1.0
Requires-Dist: pandas>=2.0.0
Requires-Dist: jsonpath-ng>=1.6.0
Requires-Dist: rich>=13.0.0
Requires-Dist: scikit-learn>=1.3.0
Requires-Dist: joblib>=1.3.0
Provides-Extra: dev
Requires-Dist: mypy>=1.11.1; extra == "dev"
Requires-Dist: ruff>=0.6.1; extra == "dev"
Requires-Dist: pytest>=7.4.0; extra == "dev"
Requires-Dist: pytest-asyncio>=0.21.0; extra == "dev"
Requires-Dist: pytest-cov>=4.1.0; extra == "dev"
Provides-Extra: notebook
Requires-Dist: nest-asyncio>=1.5.0; extra == "notebook"
Dynamic: license-file
